huibiao_framework/__init__.py
huibiao_framework/backend/__init__.py
huibiao_framework/backend/exception.py
huibiao_framework/backend/handler.py
huibiao_framework/backend/status_code.py
huibiao_framework/backend/utils.py
huibiao_framework/backend/vo.py
huibiao_framework/backend/intercept/__init__.py
huibiao_framework/backend/intercept/http.py
huibiao_framework/backend/intercept/validate.py
huibiao_framework/backend/log_utils/__init__.py
huibiao_framework/backend/log_utils/log_clean.py
huibiao_framework/backend/log_utils/log_setup.py
huibiao_framework/backend/metrics/__init__.py
huibiao_framework/backend/metrics/request_metrics.py
huibiao_framework/client/__init__.py
huibiao_framework/client/abstract_client.py
huibiao_framework/client/chunk_client.py
huibiao_framework/client/embed_client.py
huibiao_framework/client/minio_client.py
huibiao_framework/client/qa_search.py
huibiao_framework/client/data_model/__init__.py
huibiao_framework/client/data_model/chunk.py
huibiao_framework/client/data_model/embed.py
huibiao_framework/client/data_model/model_resp_vo.py
huibiao_framework/client/data_model/qa_search.py
huibiao_framework/client/data_model/vllm.py
huibiao_framework/client/data_model/ocr/__init__.py
huibiao_framework/client/data_model/ocr/image_ocr.py
huibiao_framework/client/data_model/ocr/layout_detect_vo.py
huibiao_framework/client/llm/__init__.py
huibiao_framework/client/llm/abstrast_llm_client.py
huibiao_framework/client/llm/huize_qwen32b_awq_client.py
huibiao_framework/client/llm/llm_client.py
huibiao_framework/client/tender_ocr/__init__.py
huibiao_framework/client/tender_ocr/image_ocr_client.py
huibiao_framework/client/tender_ocr/layout_detect_client.py
huibiao_framework/config/__init__.py
huibiao_framework/config/config.py
huibiao_framework/execption/__init__.py
huibiao_framework/execption/execption.py
huibiao_framework/execption/minio.py
huibiao_framework/execption/model.py
huibiao_framework/pool_executor/__init__.py
huibiao_framework/pool_executor/executor.py
huibiao_framework-1.0.17.20250929.dist-info/METADATA
huibiao_framework-1.0.17.20250929.dist-info/WHEEL
huibiao_framework-1.0.17.20250929.dist-info/top_level.txt
huibiao_framework-1.0.17.20250929.dist-info/RECORD
