Metadata-Version: 2.4
Name: huibiao-framework
Version: 1.0.17.20250929
Summary: Huibioa framework.
Requires-Python: >=3.10
Requires-Dist: aiofiles>=24.1.0
Requires-Dist: aiohttp>=3.12.13
Requires-Dist: fastapi>=0.116.1
Requires-Dist: loguru>=0.7.3
Requires-Dist: miniopy-async>=1.23.2
Requires-Dist: prometheus-client>=0.22.1
Requires-Dist: pydantic>=2.11.7
Requires-Dist: pytest>=8.4.2
Requires-Dist: python-dotenv>=1.1.1
